[
  {
    "unitCnt": 4,
    "setId": 1,
    "unitId": 4,
    "poolId": 1,
    "rinterval": 6,
    "formationN": 0,
    "unitType": 5,
    "id": 1,
    "stime": 0.1
  },
  {
    "unitCnt": 3,
    "setId": 1,
    "unitId": 5,
    "poolId": 1,
    "rinterval": 6,
    "formationN": 0,
    "unitType": 5,
    "id": 2,
    "stime": 1
  },
  {
    "unitCnt": 2,
    "setId": 1,
    "unitId": 8,
    "poolId": 1,
    "rinterval": 6,
    "formationN": 0,
    "unitType": 5,
    "id": 3,
    "stime": 2
  },
  {
    "unitCnt": 1,
    "setId": 1,
    "unitId": 29,
    "poolId": 1,
    "rinterval": 0,
    "formationN": 0,
    "unitType": 6,
    "id": 4,
    "stime": 0
  },
  {
    "unitCnt": 1,
    "setId": 2,
    "unitId": 21,
    "poolId": 1,
    "rinterval": 6,
    "formationN": 0,
    "unitType": 5,
    "id": 5,
    "stime": 0.1
  },
  {
    "unitCnt": 1,
    "setId": 2,
    "unitId": 7,
    "poolId": 1,
    "rinterval": 6,
    "formationN": 0,
    "unitType": 5,
    "id": 6,
    "stime": 1
  },
  {
    "unitCnt": 1,
    "setId": 2,
    "unitId": 19,
    "poolId": 1,
    "rinterval": 6,
    "formationN": 0,
    "unitType": 5,
    "id": 7,
    "stime": 2
  },
  {
    "unitCnt": 1,
    "setId": 2,
    "unitId": 30,
    "poolId": 1,
    "rinterval": 0,
    "formationN": 0,
    "unitType": 6,
    "id": 8,
    "stime": 0
  },
  {
    "unitCnt": 4,
    "setId": 3,
    "unitId": 8,
    "poolId": 1,
    "rinterval": 6,
    "formationN": 0,
    "unitType": 5,
    "id": 9,
    "stime": 0.1
  },
  {
    "unitCnt": 2,
    "setId": 3,
    "unitId": 26,
    "poolId": 1,
    "rinterval": 6,
    "formationN": 0,
    "unitType": 5,
    "id": 10,
    "stime": 1
  },
  {
    "unitCnt": 1,
    "setId": 3,
    "unitId": 17,
    "poolId": 1,
    "rinterval": 6,
    "formationN": 0,
    "unitType": 5,
    "id": 11,
    "stime": 2
  },
  {
    "unitCnt": 1,
    "setId": 3,
    "unitId": 31,
    "poolId": 1,
    "rinterval": 0,
    "formationN": 0,
    "unitType": 6,
    "id": 12,
    "stime": 0
  },
  {
    "unitCnt": 4,
    "setId": 4,
    "unitId": 2,
    "poolId": 1,
    "rinterval": 6,
    "formationN": 2,
    "unitType": 5,
    "id": 13,
    "stime": 0.1
  },
  {
    "unitCnt": 3,
    "setId": 4,
    "unitId": 3,
    "poolId": 1,
    "rinterval": 6,
    "formationN": 3,
    "unitType": 5,
    "id": 14,
    "stime": 1
  },
  {
    "unitCnt": 2,
    "setId": 4,
    "unitId": 9,
    "poolId": 1,
    "rinterval": 6,
    "formationN": 2,
    "unitType": 5,
    "id": 15,
    "stime": 2
  },
  {
    "unitCnt": 1,
    "setId": 4,
    "unitId": 29,
    "poolId": 1,
    "rinterval": 0,
    "formationN": 0,
    "unitType": 6,
    "id": 16,
    "stime": 0
  },
  {
    "unitCnt": 1,
    "setId": 5,
    "unitId": 16,
    "poolId": 1,
    "rinterval": 6,
    "formationN": 1,
    "unitType": 5,
    "id": 17,
    "stime": 0.1
  },
  {
    "unitCnt": 1,
    "setId": 5,
    "unitId": 22,
    "poolId": 1,
    "rinterval": 6,
    "formationN": 1,
    "unitType": 5,
    "id": 18,
    "stime": 1
  },
  {
    "unitCnt": 1,
    "setId": 5,
    "unitId": 13,
    "poolId": 1,
    "rinterval": 6,
    "formationN": 1,
    "unitType": 5,
    "id": 19,
    "stime": 2
  },
  {
    "unitCnt": 1,
    "setId": 5,
    "unitId": 30,
    "poolId": 1,
    "rinterval": 0,
    "formationN": 0,
    "unitType": 6,
    "id": 20,
    "stime": 0
  },
  {
    "unitCnt": 4,
    "setId": 6,
    "unitId": 2,
    "poolId": 1,
    "rinterval": 6,
    "formationN": 4,
    "unitType": 5,
    "id": 21,
    "stime": 0.1
  },
  {
    "unitCnt": 2,
    "setId": 6,
    "unitId": 7,
    "poolId": 1,
    "rinterval": 6,
    "formationN": 2,
    "unitType": 5,
    "id": 22,
    "stime": 1
  },
  {
    "unitCnt": 1,
    "setId": 6,
    "unitId": 18,
    "poolId": 1,
    "rinterval": 6,
    "formationN": 1,
    "unitType": 5,
    "id": 23,
    "stime": 2
  },
  {
    "unitCnt": 1,
    "setId": 6,
    "unitId": 31,
    "poolId": 1,
    "rinterval": 0,
    "formationN": 0,
    "unitType": 6,
    "id": 24,
    "stime": 0
  },
  {
    "unitCnt": 6,
    "setId": 1,
    "unitId": 8,
    "poolId": 2,
    "rinterval": 6,
    "formationN": 0,
    "unitType": 5,
    "id": 25,
    "stime": 0.1
  },
  {
    "unitCnt": 4,
    "setId": 1,
    "unitId": 4,
    "poolId": 2,
    "rinterval": 6,
    "formationN": 0,
    "unitType": 5,
    "id": 26,
    "stime": 1
  },
  {
    "unitCnt": 2,
    "setId": 1,
    "unitId": 5,
    "poolId": 2,
    "rinterval": 6,
    "formationN": 0,
    "unitType": 5,
    "id": 27,
    "stime": 2
  },
  {
    "unitCnt": 1,
    "setId": 1,
    "unitId": 32,
    "poolId": 2,
    "rinterval": 0,
    "formationN": 0,
    "unitType": 6,
    "id": 28,
    "stime": 0
  },
  {
    "unitCnt": 1,
    "setId": 2,
    "unitId": 21,
    "poolId": 2,
    "rinterval": 6,
    "formationN": 0,
    "unitType": 5,
    "id": 29,
    "stime": 0.1
  },
  {
    "unitCnt": 2,
    "setId": 2,
    "unitId": 7,
    "poolId": 2,
    "rinterval": 6,
    "formationN": 0,
    "unitType": 5,
    "id": 30,
    "stime": 1
  },
  {
    "unitCnt": 1,
    "setId": 2,
    "unitId": 19,
    "poolId": 2,
    "rinterval": 6,
    "formationN": 0,
    "unitType": 5,
    "id": 31,
    "stime": 2
  },
  {
    "unitCnt": 1,
    "setId": 2,
    "unitId": 33,
    "poolId": 2,
    "rinterval": 0,
    "formationN": 0,
    "unitType": 6,
    "id": 32,
    "stime": 0
  },
  {
    "unitCnt": 6,
    "setId": 3,
    "unitId": 3,
    "poolId": 2,
    "rinterval": 6,
    "formationN": 0,
    "unitType": 5,
    "id": 33,
    "stime": 0.1
  },
  {
    "unitCnt": 4,
    "setId": 3,
    "unitId": 9,
    "poolId": 2,
    "rinterval": 6,
    "formationN": 0,
    "unitType": 5,
    "id": 34,
    "stime": 1
  },
  {
    "unitCnt": 2,
    "setId": 3,
    "unitId": 2,
    "poolId": 2,
    "rinterval": 6,
    "formationN": 0,
    "unitType": 5,
    "id": 35,
    "stime": 2
  },
  {
    "unitCnt": 1,
    "setId": 3,
    "unitId": 34,
    "poolId": 2,
    "rinterval": 0,
    "formationN": 0,
    "unitType": 6,
    "id": 36,
    "stime": 0
  },
  {
    "unitCnt": 4,
    "setId": 4,
    "unitId": 5,
    "poolId": 2,
    "rinterval": 6,
    "formationN": 0,
    "unitType": 5,
    "id": 37,
    "stime": 0.1
  },
  {
    "unitCnt": 3,
    "setId": 4,
    "unitId": 6,
    "poolId": 2,
    "rinterval": 6,
    "formationN": 0,
    "unitType": 5,
    "id": 38,
    "stime": 1
  },
  {
    "unitCnt": 1,
    "setId": 4,
    "unitId": 13,
    "poolId": 2,
    "rinterval": 6,
    "formationN": 0,
    "unitType": 5,
    "id": 39,
    "stime": 2
  },
  {
    "unitCnt": 1,
    "setId": 4,
    "unitId": 35,
    "poolId": 2,
    "rinterval": 0,
    "formationN": 0,
    "unitType": 6,
    "id": 40,
    "stime": 0
  },
  {
    "unitCnt": 6,
    "setId": 5,
    "unitId": 9,
    "poolId": 2,
    "rinterval": 6,
    "formationN": 3,
    "unitType": 5,
    "id": 41,
    "stime": 0.1
  },
  {
    "unitCnt": 4,
    "setId": 5,
    "unitId": 2,
    "poolId": 2,
    "rinterval": 6,
    "formationN": 2,
    "unitType": 5,
    "id": 42,
    "stime": 1
  },
  {
    "unitCnt": 2,
    "setId": 5,
    "unitId": 3,
    "poolId": 2,
    "rinterval": 6,
    "formationN": 2,
    "unitType": 5,
    "id": 43,
    "stime": 2
  },
  {
    "unitCnt": 1,
    "setId": 5,
    "unitId": 32,
    "poolId": 2,
    "rinterval": 0,
    "formationN": 0,
    "unitType": 6,
    "id": 44,
    "stime": 0
  },
  {
    "unitCnt": 1,
    "setId": 6,
    "unitId": 16,
    "poolId": 2,
    "rinterval": 6,
    "formationN": 1,
    "unitType": 5,
    "id": 45,
    "stime": 0.1
  },
  {
    "unitCnt": 2,
    "setId": 6,
    "unitId": 26,
    "poolId": 2,
    "rinterval": 6,
    "formationN": 2,
    "unitType": 5,
    "id": 46,
    "stime": 1
  },
  {
    "unitCnt": 1,
    "setId": 6,
    "unitId": 12,
    "poolId": 2,
    "rinterval": 6,
    "formationN": 1,
    "unitType": 5,
    "id": 47,
    "stime": 2
  },
  {
    "unitCnt": 1,
    "setId": 6,
    "unitId": 33,
    "poolId": 2,
    "rinterval": 0,
    "formationN": 0,
    "unitType": 6,
    "id": 48,
    "stime": 0
  },
  {
    "unitCnt": 6,
    "setId": 7,
    "unitId": 5,
    "poolId": 2,
    "rinterval": 6,
    "formationN": 3,
    "unitType": 5,
    "id": 49,
    "stime": 0.1
  },
  {
    "unitCnt": 4,
    "setId": 7,
    "unitId": 15,
    "poolId": 2,
    "rinterval": 6,
    "formationN": 2,
    "unitType": 5,
    "id": 50,
    "stime": 1
  },
  {
    "unitCnt": 2,
    "setId": 7,
    "unitId": 4,
    "poolId": 2,
    "rinterval": 6,
    "formationN": 2,
    "unitType": 5,
    "id": 51,
    "stime": 2
  },
  {
    "unitCnt": 1,
    "setId": 7,
    "unitId": 34,
    "poolId": 2,
    "rinterval": 0,
    "formationN": 0,
    "unitType": 6,
    "id": 52,
    "stime": 0
  },
  {
    "unitCnt": 4,
    "setId": 8,
    "unitId": 8,
    "poolId": 2,
    "rinterval": 6,
    "formationN": 2,
    "unitType": 5,
    "id": 53,
    "stime": 0.1
  },
  {
    "unitCnt": 3,
    "setId": 8,
    "unitId": 22,
    "poolId": 2,
    "rinterval": 6,
    "formationN": 3,
    "unitType": 5,
    "id": 54,
    "stime": 1
  },
  {
    "unitCnt": 1,
    "setId": 8,
    "unitId": 10,
    "poolId": 2,
    "rinterval": 6,
    "formationN": 1,
    "unitType": 5,
    "id": 55,
    "stime": 2
  },
  {
    "unitCnt": 1,
    "setId": 8,
    "unitId": 35,
    "poolId": 2,
    "rinterval": 0,
    "formationN": 0,
    "unitType": 6,
    "id": 56,
    "stime": 0
  },
  {
    "unitCnt": 6,
    "setId": 1,
    "unitId": 5,
    "poolId": 3,
    "rinterval": 6,
    "formationN": 0,
    "unitType": 5,
    "id": 57,
    "stime": 0.1
  },
  {
    "unitCnt": 5,
    "setId": 1,
    "unitId": 9,
    "poolId": 3,
    "rinterval": 6,
    "formationN": 0,
    "unitType": 5,
    "id": 58,
    "stime": 1
  },
  {
    "unitCnt": 4,
    "setId": 1,
    "unitId": 4,
    "poolId": 3,
    "rinterval": 6,
    "formationN": 0,
    "unitType": 5,
    "id": 59,
    "stime": 2
  },
  {
    "unitCnt": 1,
    "setId": 1,
    "unitId": 36,
    "poolId": 3,
    "rinterval": 0,
    "formationN": 0,
    "unitType": 6,
    "id": 60,
    "stime": 0
  },
  {
    "unitCnt": 2,
    "setId": 2,
    "unitId": 16,
    "poolId": 3,
    "rinterval": 6,
    "formationN": 0,
    "unitType": 5,
    "id": 61,
    "stime": 0.1
  },
  {
    "unitCnt": 2,
    "setId": 2,
    "unitId": 7,
    "poolId": 3,
    "rinterval": 6,
    "formationN": 0,
    "unitType": 5,
    "id": 62,
    "stime": 1
  },
  {
    "unitCnt": 1,
    "setId": 2,
    "unitId": 12,
    "poolId": 3,
    "rinterval": 6,
    "formationN": 0,
    "unitType": 5,
    "id": 63,
    "stime": 2
  },
  {
    "unitCnt": 1,
    "setId": 2,
    "unitId": 37,
    "poolId": 3,
    "rinterval": 0,
    "formationN": 0,
    "unitType": 6,
    "id": 64,
    "stime": 0
  },
  {
    "unitCnt": 6,
    "setId": 3,
    "unitId": 2,
    "poolId": 3,
    "rinterval": 6,
    "formationN": 0,
    "unitType": 5,
    "id": 65,
    "stime": 0.1
  },
  {
    "unitCnt": 5,
    "setId": 3,
    "unitId": 4,
    "poolId": 3,
    "rinterval": 6,
    "formationN": 0,
    "unitType": 5,
    "id": 66,
    "stime": 1
  },
  {
    "unitCnt": 4,
    "setId": 3,
    "unitId": 3,
    "poolId": 3,
    "rinterval": 6,
    "formationN": 0,
    "unitType": 5,
    "id": 67,
    "stime": 2
  },
  {
    "unitCnt": 1,
    "setId": 3,
    "unitId": 38,
    "poolId": 3,
    "rinterval": 0,
    "formationN": 0,
    "unitType": 6,
    "id": 68,
    "stime": 0
  },
  {
    "unitCnt": 2,
    "setId": 4,
    "unitId": 16,
    "poolId": 3,
    "rinterval": 6,
    "formationN": 0,
    "unitType": 5,
    "id": 69,
    "stime": 0.1
  },
  {
    "unitCnt": 2,
    "setId": 4,
    "unitId": 6,
    "poolId": 3,
    "rinterval": 6,
    "formationN": 0,
    "unitType": 5,
    "id": 70,
    "stime": 1
  },
  {
    "unitCnt": 1,
    "setId": 4,
    "unitId": 19,
    "poolId": 3,
    "rinterval": 6,
    "formationN": 0,
    "unitType": 5,
    "id": 71,
    "stime": 2
  },
  {
    "unitCnt": 1,
    "setId": 4,
    "unitId": 39,
    "poolId": 3,
    "rinterval": 0,
    "formationN": 0,
    "unitType": 6,
    "id": 72,
    "stime": 0
  },
  {
    "unitCnt": 6,
    "setId": 5,
    "unitId": 2,
    "poolId": 3,
    "rinterval": 6,
    "formationN": 0,
    "unitType": 5,
    "id": 73,
    "stime": 0.1
  },
  {
    "unitCnt": 4,
    "setId": 5,
    "unitId": 22,
    "poolId": 3,
    "rinterval": 6,
    "formationN": 0,
    "unitType": 5,
    "id": 74,
    "stime": 1
  },
  {
    "unitCnt": 1,
    "setId": 5,
    "unitId": 18,
    "poolId": 3,
    "rinterval": 6,
    "formationN": 0,
    "unitType": 5,
    "id": 75,
    "stime": 2
  },
  {
    "unitCnt": 1,
    "setId": 5,
    "unitId": 40,
    "poolId": 3,
    "rinterval": 0,
    "formationN": 0,
    "unitType": 6,
    "id": 76,
    "stime": 0
  },
  {
    "unitCnt": 6,
    "setId": 6,
    "unitId": 8,
    "poolId": 3,
    "rinterval": 6,
    "formationN": 3,
    "unitType": 5,
    "id": 77,
    "stime": 0.1
  },
  {
    "unitCnt": 5,
    "setId": 6,
    "unitId": 2,
    "poolId": 3,
    "rinterval": 6,
    "formationN": 5,
    "unitType": 5,
    "id": 78,
    "stime": 1
  },
  {
    "unitCnt": 4,
    "setId": 6,
    "unitId": 4,
    "poolId": 3,
    "rinterval": 6,
    "formationN": 4,
    "unitType": 5,
    "id": 79,
    "stime": 2
  },
  {
    "unitCnt": 1,
    "setId": 6,
    "unitId": 36,
    "poolId": 3,
    "rinterval": 0,
    "formationN": 0,
    "unitType": 6,
    "id": 80,
    "stime": 0
  },
  {
    "unitCnt": 2,
    "setId": 7,
    "unitId": 6,
    "poolId": 3,
    "rinterval": 6,
    "formationN": 2,
    "unitType": 5,
    "id": 81,
    "stime": 0.1
  },
  {
    "unitCnt": 2,
    "setId": 7,
    "unitId": 7,
    "poolId": 3,
    "rinterval": 6,
    "formationN": 2,
    "unitType": 5,
    "id": 82,
    "stime": 1
  },
  {
    "unitCnt": 1,
    "setId": 7,
    "unitId": 13,
    "poolId": 3,
    "rinterval": 6,
    "formationN": 1,
    "unitType": 5,
    "id": 83,
    "stime": 2
  },
  {
    "unitCnt": 1,
    "setId": 7,
    "unitId": 37,
    "poolId": 3,
    "rinterval": 0,
    "formationN": 0,
    "unitType": 6,
    "id": 84,
    "stime": 0
  },
  {
    "unitCnt": 6,
    "setId": 8,
    "unitId": 8,
    "poolId": 3,
    "rinterval": 6,
    "formationN": 3,
    "unitType": 5,
    "id": 85,
    "stime": 0.1
  },
  {
    "unitCnt": 5,
    "setId": 8,
    "unitId": 15,
    "poolId": 3,
    "rinterval": 6,
    "formationN": 5,
    "unitType": 5,
    "id": 86,
    "stime": 1
  },
  {
    "unitCnt": 4,
    "setId": 8,
    "unitId": 3,
    "poolId": 3,
    "rinterval": 6,
    "formationN": 4,
    "unitType": 5,
    "id": 87,
    "stime": 2
  },
  {
    "unitCnt": 1,
    "setId": 8,
    "unitId": 38,
    "poolId": 3,
    "rinterval": 0,
    "formationN": 0,
    "unitType": 6,
    "id": 88,
    "stime": 0
  },
  {
    "unitCnt": 2,
    "setId": 9,
    "unitId": 6,
    "poolId": 3,
    "rinterval": 6,
    "formationN": 2,
    "unitType": 5,
    "id": 89,
    "stime": 0.1
  },
  {
    "unitCnt": 2,
    "setId": 9,
    "unitId": 16,
    "poolId": 3,
    "rinterval": 6,
    "formationN": 2,
    "unitType": 5,
    "id": 90,
    "stime": 1
  },
  {
    "unitCnt": 1,
    "setId": 9,
    "unitId": 12,
    "poolId": 3,
    "rinterval": 6,
    "formationN": 1,
    "unitType": 5,
    "id": 91,
    "stime": 2
  },
  {
    "unitCnt": 1,
    "setId": 9,
    "unitId": 39,
    "poolId": 3,
    "rinterval": 0,
    "formationN": 0,
    "unitType": 6,
    "id": 92,
    "stime": 0
  },
  {
    "unitCnt": 6,
    "setId": 10,
    "unitId": 3,
    "poolId": 3,
    "rinterval": 6,
    "formationN": 3,
    "unitType": 5,
    "id": 93,
    "stime": 0.1
  },
  {
    "unitCnt": 4,
    "setId": 10,
    "unitId": 6,
    "poolId": 3,
    "rinterval": 6,
    "formationN": 2,
    "unitType": 5,
    "id": 94,
    "stime": 1
  },
  {
    "unitCnt": 1,
    "setId": 10,
    "unitId": 18,
    "poolId": 3,
    "rinterval": 6,
    "formationN": 1,
    "unitType": 5,
    "id": 95,
    "stime": 2
  },
  {
    "unitCnt": 1,
    "setId": 10,
    "unitId": 40,
    "poolId": 3,
    "rinterval": 0,
    "formationN": 0,
    "unitType": 6,
    "id": 96,
    "stime": 0
  },
  {
    "unitCnt": 8,
    "setId": 1,
    "unitId": 15,
    "poolId": 4,
    "rinterval": 6,
    "formationN": 0,
    "unitType": 5,
    "id": 97,
    "stime": 0.1
  },
  {
    "unitCnt": 6,
    "setId": 1,
    "unitId": 3,
    "poolId": 4,
    "rinterval": 6,
    "formationN": 0,
    "unitType": 5,
    "id": 98,
    "stime": 1
  },
  {
    "unitCnt": 4,
    "setId": 1,
    "unitId": 4,
    "poolId": 4,
    "rinterval": 6,
    "formationN": 0,
    "unitType": 5,
    "id": 99,
    "stime": 2
  },
  {
    "unitCnt": 1,
    "setId": 1,
    "unitId": 41,
    "poolId": 4,
    "rinterval": 0,
    "formationN": 0,
    "unitType": 6,
    "id": 100,
    "stime": 0
  },
  {
    "unitCnt": 2,
    "setId": 2,
    "unitId": 26,
    "poolId": 4,
    "rinterval": 6,
    "formationN": 0,
    "unitType": 5,
    "id": 101,
    "stime": 0.1
  },
  {
    "unitCnt": 3,
    "setId": 2,
    "unitId": 6,
    "poolId": 4,
    "rinterval": 6,
    "formationN": 0,
    "unitType": 5,
    "id": 102,
    "stime": 1
  },
  {
    "unitCnt": 1,
    "setId": 2,
    "unitId": 12,
    "poolId": 4,
    "rinterval": 6,
    "formationN": 0,
    "unitType": 5,
    "id": 103,
    "stime": 2
  },
  {
    "unitCnt": 1,
    "setId": 2,
    "unitId": 42,
    "poolId": 4,
    "rinterval": 0,
    "formationN": 0,
    "unitType": 6,
    "id": 104,
    "stime": 0
  },
  {
    "unitCnt": 8,
    "setId": 3,
    "unitId": 8,
    "poolId": 4,
    "rinterval": 6,
    "formationN": 0,
    "unitType": 5,
    "id": 105,
    "stime": 0.1
  },
  {
    "unitCnt": 6,
    "setId": 3,
    "unitId": 5,
    "poolId": 4,
    "rinterval": 6,
    "formationN": 0,
    "unitType": 5,
    "id": 106,
    "stime": 1
  },
  {
    "unitCnt": 4,
    "setId": 3,
    "unitId": 4,
    "poolId": 4,
    "rinterval": 6,
    "formationN": 0,
    "unitType": 5,
    "id": 107,
    "stime": 2
  },
  {
    "unitCnt": 1,
    "setId": 3,
    "unitId": 43,
    "poolId": 4,
    "rinterval": 0,
    "formationN": 0,
    "unitType": 6,
    "id": 108,
    "stime": 0
  },
  {
    "unitCnt": 2,
    "setId": 4,
    "unitId": 22,
    "poolId": 4,
    "rinterval": 6,
    "formationN": 0,
    "unitType": 5,
    "id": 109,
    "stime": 0.1
  },
  {
    "unitCnt": 3,
    "setId": 4,
    "unitId": 26,
    "poolId": 4,
    "rinterval": 6,
    "formationN": 0,
    "unitType": 5,
    "id": 110,
    "stime": 1
  },
  {
    "unitCnt": 1,
    "setId": 4,
    "unitId": 19,
    "poolId": 4,
    "rinterval": 6,
    "formationN": 0,
    "unitType": 5,
    "id": 111,
    "stime": 2
  },
  {
    "unitCnt": 1,
    "setId": 4,
    "unitId": 44,
    "poolId": 4,
    "rinterval": 0,
    "formationN": 0,
    "unitType": 6,
    "id": 112,
    "stime": 0
  },
  {
    "unitCnt": 8,
    "setId": 5,
    "unitId": 4,
    "poolId": 4,
    "rinterval": 6,
    "formationN": 0,
    "unitType": 5,
    "id": 113,
    "stime": 0.1
  },
  {
    "unitCnt": 6,
    "setId": 5,
    "unitId": 8,
    "poolId": 4,
    "rinterval": 6,
    "formationN": 0,
    "unitType": 5,
    "id": 114,
    "stime": 1
  },
  {
    "unitCnt": 4,
    "setId": 5,
    "unitId": 3,
    "poolId": 4,
    "rinterval": 6,
    "formationN": 0,
    "unitType": 5,
    "id": 115,
    "stime": 2
  },
  {
    "unitCnt": 1,
    "setId": 5,
    "unitId": 45,
    "poolId": 4,
    "rinterval": 0,
    "formationN": 0,
    "unitType": 6,
    "id": 116,
    "stime": 0
  },
  {
    "unitCnt": 5,
    "setId": 6,
    "unitId": 3,
    "poolId": 4,
    "rinterval": 6,
    "formationN": 0,
    "unitType": 5,
    "id": 117,
    "stime": 0.1
  },
  {
    "unitCnt": 4,
    "setId": 6,
    "unitId": 6,
    "poolId": 4,
    "rinterval": 6,
    "formationN": 0,
    "unitType": 5,
    "id": 118,
    "stime": 1
  },
  {
    "unitCnt": 2,
    "setId": 6,
    "unitId": 17,
    "poolId": 4,
    "rinterval": 6,
    "formationN": 0,
    "unitType": 5,
    "id": 119,
    "stime": 2
  },
  {
    "unitCnt": 1,
    "setId": 6,
    "unitId": 46,
    "poolId": 4,
    "rinterval": 0,
    "formationN": 0,
    "unitType": 6,
    "id": 120,
    "stime": 0
  },
  {
    "unitCnt": 8,
    "setId": 7,
    "unitId": 3,
    "poolId": 4,
    "rinterval": 6,
    "formationN": 4,
    "unitType": 5,
    "id": 121,
    "stime": 0.1
  },
  {
    "unitCnt": 6,
    "setId": 7,
    "unitId": 2,
    "poolId": 4,
    "rinterval": 6,
    "formationN": 3,
    "unitType": 5,
    "id": 122,
    "stime": 1
  },
  {
    "unitCnt": 4,
    "setId": 7,
    "unitId": 4,
    "poolId": 4,
    "rinterval": 6,
    "formationN": 2,
    "unitType": 5,
    "id": 123,
    "stime": 2
  },
  {
    "unitCnt": 1,
    "setId": 7,
    "unitId": 41,
    "poolId": 4,
    "rinterval": 0,
    "formationN": 0,
    "unitType": 6,
    "id": 124,
    "stime": 0
  },
  {
    "unitCnt": 2,
    "setId": 8,
    "unitId": 26,
    "poolId": 4,
    "rinterval": 6,
    "formationN": 2,
    "unitType": 5,
    "id": 125,
    "stime": 0.1
  },
  {
    "unitCnt": 3,
    "setId": 8,
    "unitId": 22,
    "poolId": 4,
    "rinterval": 6,
    "formationN": 3,
    "unitType": 5,
    "id": 126,
    "stime": 1
  },
  {
    "unitCnt": 1,
    "setId": 8,
    "unitId": 13,
    "poolId": 4,
    "rinterval": 6,
    "formationN": 1,
    "unitType": 5,
    "id": 127,
    "stime": 2
  },
  {
    "unitCnt": 1,
    "setId": 8,
    "unitId": 42,
    "poolId": 4,
    "rinterval": 0,
    "formationN": 0,
    "unitType": 6,
    "id": 128,
    "stime": 0
  },
  {
    "unitCnt": 8,
    "setId": 9,
    "unitId": 8,
    "poolId": 4,
    "rinterval": 6,
    "formationN": 4,
    "unitType": 5,
    "id": 129,
    "stime": 0.1
  },
  {
    "unitCnt": 6,
    "setId": 9,
    "unitId": 15,
    "poolId": 4,
    "rinterval": 6,
    "formationN": 3,
    "unitType": 5,
    "id": 130,
    "stime": 1
  },
  {
    "unitCnt": 4,
    "setId": 9,
    "unitId": 2,
    "poolId": 4,
    "rinterval": 6,
    "formationN": 2,
    "unitType": 5,
    "id": 131,
    "stime": 2
  },
  {
    "unitCnt": 1,
    "setId": 9,
    "unitId": 43,
    "poolId": 4,
    "rinterval": 0,
    "formationN": 0,
    "unitType": 6,
    "id": 132,
    "stime": 0
  },
  {
    "unitCnt": 2,
    "setId": 10,
    "unitId": 7,
    "poolId": 4,
    "rinterval": 6,
    "formationN": 2,
    "unitType": 5,
    "id": 133,
    "stime": 0.1
  },
  {
    "unitCnt": 3,
    "setId": 10,
    "unitId": 6,
    "poolId": 4,
    "rinterval": 6,
    "formationN": 3,
    "unitType": 5,
    "id": 134,
    "stime": 1
  },
  {
    "unitCnt": 1,
    "setId": 10,
    "unitId": 10,
    "poolId": 4,
    "rinterval": 6,
    "formationN": 1,
    "unitType": 5,
    "id": 135,
    "stime": 2
  },
  {
    "unitCnt": 1,
    "setId": 10,
    "unitId": 44,
    "poolId": 4,
    "rinterval": 0,
    "formationN": 0,
    "unitType": 6,
    "id": 136,
    "stime": 0
  },
  {
    "unitCnt": 8,
    "setId": 11,
    "unitId": 3,
    "poolId": 4,
    "rinterval": 6,
    "formationN": 4,
    "unitType": 5,
    "id": 137,
    "stime": 0.1
  },
  {
    "unitCnt": 6,
    "setId": 11,
    "unitId": 4,
    "poolId": 4,
    "rinterval": 6,
    "formationN": 3,
    "unitType": 5,
    "id": 138,
    "stime": 1
  },
  {
    "unitCnt": 4,
    "setId": 11,
    "unitId": 9,
    "poolId": 4,
    "rinterval": 6,
    "formationN": 2,
    "unitType": 5,
    "id": 139,
    "stime": 2
  },
  {
    "unitCnt": 1,
    "setId": 11,
    "unitId": 45,
    "poolId": 4,
    "rinterval": 0,
    "formationN": 0,
    "unitType": 6,
    "id": 140,
    "stime": 0
  },
  {
    "unitCnt": 5,
    "setId": 12,
    "unitId": 15,
    "poolId": 4,
    "rinterval": 6,
    "formationN": 5,
    "unitType": 5,
    "id": 141,
    "stime": 0.1
  },
  {
    "unitCnt": 4,
    "setId": 12,
    "unitId": 26,
    "poolId": 4,
    "rinterval": 6,
    "formationN": 2,
    "unitType": 5,
    "id": 142,
    "stime": 1
  },
  {
    "unitCnt": 2,
    "setId": 12,
    "unitId": 19,
    "poolId": 4,
    "rinterval": 6,
    "formationN": 2,
    "unitType": 5,
    "id": 143,
    "stime": 2
  },
  {
    "unitCnt": 1,
    "setId": 12,
    "unitId": 46,
    "poolId": 4,
    "rinterval": 0,
    "formationN": 0,
    "unitType": 6,
    "id": 144,
    "stime": 0
  },
  {
    "unitCnt": 8,
    "setId": 1,
    "unitId": 15,
    "poolId": 5,
    "rinterval": 6,
    "formationN": 0,
    "unitType": 5,
    "id": 145,
    "stime": 0.1
  },
  {
    "unitCnt": 6,
    "setId": 1,
    "unitId": 8,
    "poolId": 5,
    "rinterval": 6,
    "formationN": 0,
    "unitType": 5,
    "id": 146,
    "stime": 1
  },
  {
    "unitCnt": 6,
    "setId": 1,
    "unitId": 9,
    "poolId": 5,
    "rinterval": 6,
    "formationN": 0,
    "unitType": 5,
    "id": 147,
    "stime": 2
  },
  {
    "unitCnt": 1,
    "setId": 1,
    "unitId": 47,
    "poolId": 5,
    "rinterval": 0,
    "formationN": 0,
    "unitType": 6,
    "id": 148,
    "stime": 0
  },
  {
    "unitCnt": 2,
    "setId": 2,
    "unitId": 7,
    "poolId": 5,
    "rinterval": 6,
    "formationN": 0,
    "unitType": 5,
    "id": 149,
    "stime": 0.1
  },
  {
    "unitCnt": 3,
    "setId": 2,
    "unitId": 26,
    "poolId": 5,
    "rinterval": 6,
    "formationN": 0,
    "unitType": 5,
    "id": 150,
    "stime": 1
  },
  {
    "unitCnt": 2,
    "setId": 2,
    "unitId": 12,
    "poolId": 5,
    "rinterval": 6,
    "formationN": 0,
    "unitType": 5,
    "id": 151,
    "stime": 2
  },
  {
    "unitCnt": 1,
    "setId": 2,
    "unitId": 48,
    "poolId": 5,
    "rinterval": 0,
    "formationN": 0,
    "unitType": 6,
    "id": 152,
    "stime": 0
  },
  {
    "unitCnt": 8,
    "setId": 3,
    "unitId": 8,
    "poolId": 5,
    "rinterval": 6,
    "formationN": 0,
    "unitType": 5,
    "id": 153,
    "stime": 0.1
  },
  {
    "unitCnt": 6,
    "setId": 3,
    "unitId": 2,
    "poolId": 5,
    "rinterval": 6,
    "formationN": 0,
    "unitType": 5,
    "id": 154,
    "stime": 1
  },
  {
    "unitCnt": 6,
    "setId": 3,
    "unitId": 9,
    "poolId": 5,
    "rinterval": 6,
    "formationN": 0,
    "unitType": 5,
    "id": 155,
    "stime": 2
  },
  {
    "unitCnt": 1,
    "setId": 3,
    "unitId": 49,
    "poolId": 5,
    "rinterval": 0,
    "formationN": 0,
    "unitType": 6,
    "id": 156,
    "stime": 0
  },
  {
    "unitCnt": 2,
    "setId": 4,
    "unitId": 6,
    "poolId": 5,
    "rinterval": 6,
    "formationN": 0,
    "unitType": 5,
    "id": 157,
    "stime": 0.1
  },
  {
    "unitCnt": 3,
    "setId": 4,
    "unitId": 7,
    "poolId": 5,
    "rinterval": 6,
    "formationN": 0,
    "unitType": 5,
    "id": 158,
    "stime": 1
  },
  {
    "unitCnt": 2,
    "setId": 4,
    "unitId": 12,
    "poolId": 5,
    "rinterval": 6,
    "formationN": 0,
    "unitType": 5,
    "id": 159,
    "stime": 2
  },
  {
    "unitCnt": 1,
    "setId": 4,
    "unitId": 50,
    "poolId": 5,
    "rinterval": 0,
    "formationN": 0,
    "unitType": 6,
    "id": 160,
    "stime": 0
  },
  {
    "unitCnt": 8,
    "setId": 5,
    "unitId": 9,
    "poolId": 5,
    "rinterval": 6,
    "formationN": 0,
    "unitType": 5,
    "id": 161,
    "stime": 0.1
  },
  {
    "unitCnt": 6,
    "setId": 5,
    "unitId": 8,
    "poolId": 5,
    "rinterval": 6,
    "formationN": 0,
    "unitType": 5,
    "id": 162,
    "stime": 1
  },
  {
    "unitCnt": 6,
    "setId": 5,
    "unitId": 15,
    "poolId": 5,
    "rinterval": 6,
    "formationN": 0,
    "unitType": 5,
    "id": 163,
    "stime": 2
  },
  {
    "unitCnt": 1,
    "setId": 5,
    "unitId": 29,
    "poolId": 5,
    "rinterval": 0,
    "formationN": 0,
    "unitType": 6,
    "id": 164,
    "stime": 0
  },
  {
    "unitCnt": 2,
    "setId": 6,
    "unitId": 7,
    "poolId": 5,
    "rinterval": 6,
    "formationN": 0,
    "unitType": 5,
    "id": 165,
    "stime": 0.1
  },
  {
    "unitCnt": 3,
    "setId": 6,
    "unitId": 21,
    "poolId": 5,
    "rinterval": 6,
    "formationN": 0,
    "unitType": 5,
    "id": 166,
    "stime": 1
  },
  {
    "unitCnt": 2,
    "setId": 6,
    "unitId": 18,
    "poolId": 5,
    "rinterval": 6,
    "formationN": 0,
    "unitType": 5,
    "id": 167,
    "stime": 2
  },
  {
    "unitCnt": 1,
    "setId": 6,
    "unitId": 30,
    "poolId": 5,
    "rinterval": 0,
    "formationN": 0,
    "unitType": 6,
    "id": 168,
    "stime": 0
  },
  {
    "unitCnt": 6,
    "setId": 7,
    "unitId": 3,
    "poolId": 5,
    "rinterval": 6,
    "formationN": 0,
    "unitType": 5,
    "id": 169,
    "stime": 0.1
  },
  {
    "unitCnt": 4,
    "setId": 7,
    "unitId": 6,
    "poolId": 5,
    "rinterval": 6,
    "formationN": 0,
    "unitType": 5,
    "id": 170,
    "stime": 1
  },
  {
    "unitCnt": 3,
    "setId": 7,
    "unitId": 10,
    "poolId": 5,
    "rinterval": 6,
    "formationN": 0,
    "unitType": 5,
    "id": 171,
    "stime": 2
  },
  {
    "unitCnt": 1,
    "setId": 7,
    "unitId": 31,
    "poolId": 5,
    "rinterval": 0,
    "formationN": 0,
    "unitType": 6,
    "id": 172,
    "stime": 0
  },
  {
    "unitCnt": 8,
    "setId": 8,
    "unitId": 9,
    "poolId": 5,
    "rinterval": 6,
    "formationN": 4,
    "unitType": 5,
    "id": 173,
    "stime": 0.1
  },
  {
    "unitCnt": 6,
    "setId": 8,
    "unitId": 8,
    "poolId": 5,
    "rinterval": 6,
    "formationN": 3,
    "unitType": 5,
    "id": 174,
    "stime": 1
  },
  {
    "unitCnt": 6,
    "setId": 8,
    "unitId": 3,
    "poolId": 5,
    "rinterval": 6,
    "formationN": 3,
    "unitType": 5,
    "id": 175,
    "stime": 2
  },
  {
    "unitCnt": 1,
    "setId": 8,
    "unitId": 47,
    "poolId": 5,
    "rinterval": 0,
    "formationN": 0,
    "unitType": 6,
    "id": 176,
    "stime": 0
  },
  {
    "unitCnt": 2,
    "setId": 9,
    "unitId": 7,
    "poolId": 5,
    "rinterval": 6,
    "formationN": 2,
    "unitType": 5,
    "id": 177,
    "stime": 0.1
  },
  {
    "unitCnt": 3,
    "setId": 9,
    "unitId": 16,
    "poolId": 5,
    "rinterval": 6,
    "formationN": 3,
    "unitType": 5,
    "id": 178,
    "stime": 1
  },
  {
    "unitCnt": 2,
    "setId": 9,
    "unitId": 17,
    "poolId": 5,
    "rinterval": 6,
    "formationN": 2,
    "unitType": 5,
    "id": 179,
    "stime": 2
  },
  {
    "unitCnt": 1,
    "setId": 9,
    "unitId": 48,
    "poolId": 5,
    "rinterval": 0,
    "formationN": 0,
    "unitType": 6,
    "id": 180,
    "stime": 0
  },
  {
    "unitCnt": 8,
    "setId": 10,
    "unitId": 15,
    "poolId": 5,
    "rinterval": 6,
    "formationN": 4,
    "unitType": 5,
    "id": 181,
    "stime": 0.1
  },
  {
    "unitCnt": 6,
    "setId": 10,
    "unitId": 8,
    "poolId": 5,
    "rinterval": 6,
    "formationN": 3,
    "unitType": 5,
    "id": 182,
    "stime": 1
  },
  {
    "unitCnt": 6,
    "setId": 10,
    "unitId": 2,
    "poolId": 5,
    "rinterval": 6,
    "formationN": 3,
    "unitType": 5,
    "id": 183,
    "stime": 2
  },
  {
    "unitCnt": 1,
    "setId": 10,
    "unitId": 49,
    "poolId": 5,
    "rinterval": 0,
    "formationN": 0,
    "unitType": 6,
    "id": 184,
    "stime": 0
  },
  {
    "unitCnt": 2,
    "setId": 11,
    "unitId": 21,
    "poolId": 5,
    "rinterval": 6,
    "formationN": 2,
    "unitType": 5,
    "id": 185,
    "stime": 0.1
  },
  {
    "unitCnt": 3,
    "setId": 11,
    "unitId": 7,
    "poolId": 5,
    "rinterval": 6,
    "formationN": 3,
    "unitType": 5,
    "id": 186,
    "stime": 1
  },
  {
    "unitCnt": 2,
    "setId": 11,
    "unitId": 19,
    "poolId": 5,
    "rinterval": 6,
    "formationN": 2,
    "unitType": 5,
    "id": 187,
    "stime": 2
  },
  {
    "unitCnt": 1,
    "setId": 11,
    "unitId": 50,
    "poolId": 5,
    "rinterval": 0,
    "formationN": 0,
    "unitType": 6,
    "id": 188,
    "stime": 0
  },
  {
    "unitCnt": 8,
    "setId": 12,
    "unitId": 9,
    "poolId": 5,
    "rinterval": 6,
    "formationN": 4,
    "unitType": 5,
    "id": 189,
    "stime": 0.1
  },
  {
    "unitCnt": 6,
    "setId": 12,
    "unitId": 15,
    "poolId": 5,
    "rinterval": 6,
    "formationN": 3,
    "unitType": 5,
    "id": 190,
    "stime": 1
  },
  {
    "unitCnt": 6,
    "setId": 12,
    "unitId": 3,
    "poolId": 5,
    "rinterval": 6,
    "formationN": 3,
    "unitType": 5,
    "id": 191,
    "stime": 2
  },
  {
    "unitCnt": 1,
    "setId": 12,
    "unitId": 29,
    "poolId": 5,
    "rinterval": 0,
    "formationN": 0,
    "unitType": 6,
    "id": 192,
    "stime": 0
  },
  {
    "unitCnt": 2,
    "setId": 13,
    "unitId": 7,
    "poolId": 5,
    "rinterval": 6,
    "formationN": 2,
    "unitType": 5,
    "id": 193,
    "stime": 0.1
  },
  {
    "unitCnt": 3,
    "setId": 13,
    "unitId": 22,
    "poolId": 5,
    "rinterval": 6,
    "formationN": 3,
    "unitType": 5,
    "id": 194,
    "stime": 1
  },
  {
    "unitCnt": 2,
    "setId": 13,
    "unitId": 13,
    "poolId": 5,
    "rinterval": 6,
    "formationN": 2,
    "unitType": 5,
    "id": 195,
    "stime": 2
  },
  {
    "unitCnt": 1,
    "setId": 13,
    "unitId": 30,
    "poolId": 5,
    "rinterval": 0,
    "formationN": 0,
    "unitType": 6,
    "id": 196,
    "stime": 0
  },
  {
    "unitCnt": 6,
    "setId": 14,
    "unitId": 8,
    "poolId": 5,
    "rinterval": 6,
    "formationN": 3,
    "unitType": 5,
    "id": 197,
    "stime": 0.1
  },
  {
    "unitCnt": 4,
    "setId": 14,
    "unitId": 21,
    "poolId": 5,
    "rinterval": 6,
    "formationN": 2,
    "unitType": 5,
    "id": 198,
    "stime": 1
  },
  {
    "unitCnt": 3,
    "setId": 14,
    "unitId": 12,
    "poolId": 5,
    "rinterval": 6,
    "formationN": 3,
    "unitType": 5,
    "id": 199,
    "stime": 2
  },
  {
    "unitCnt": 1,
    "setId": 14,
    "unitId": 31,
    "poolId": 5,
    "rinterval": 0,
    "formationN": 0,
    "unitType": 6,
    "id": 200,
    "stime": 0
  },
  {
    "unitCnt": 10,
    "setId": 1,
    "unitId": 8,
    "poolId": 6,
    "rinterval": 6,
    "formationN": 0,
    "unitType": 5,
    "id": 201,
    "stime": 0.1
  },
  {
    "unitCnt": 8,
    "setId": 1,
    "unitId": 15,
    "poolId": 6,
    "rinterval": 6,
    "formationN": 0,
    "unitType": 5,
    "id": 202,
    "stime": 1
  },
  {
    "unitCnt": 6,
    "setId": 1,
    "unitId": 5,
    "poolId": 6,
    "rinterval": 6,
    "formationN": 0,
    "unitType": 5,
    "id": 203,
    "stime": 2
  },
  {
    "unitCnt": 1,
    "setId": 1,
    "unitId": 32,
    "poolId": 6,
    "rinterval": 0,
    "formationN": 0,
    "unitType": 6,
    "id": 204,
    "stime": 0
  },
  {
    "unitCnt": 2,
    "setId": 2,
    "unitId": 16,
    "poolId": 6,
    "rinterval": 6,
    "formationN": 0,
    "unitType": 5,
    "id": 205,
    "stime": 0.1
  },
  {
    "unitCnt": 4,
    "setId": 2,
    "unitId": 7,
    "poolId": 6,
    "rinterval": 6,
    "formationN": 0,
    "unitType": 5,
    "id": 206,
    "stime": 1
  },
  {
    "unitCnt": 2,
    "setId": 2,
    "unitId": 13,
    "poolId": 6,
    "rinterval": 6,
    "formationN": 0,
    "unitType": 5,
    "id": 207,
    "stime": 2
  },
  {
    "unitCnt": 1,
    "setId": 2,
    "unitId": 33,
    "poolId": 6,
    "rinterval": 0,
    "formationN": 0,
    "unitType": 6,
    "id": 208,
    "stime": 0
  },
  {
    "unitCnt": 10,
    "setId": 3,
    "unitId": 8,
    "poolId": 6,
    "rinterval": 6,
    "formationN": 0,
    "unitType": 5,
    "id": 209,
    "stime": 0.1
  },
  {
    "unitCnt": 8,
    "setId": 3,
    "unitId": 5,
    "poolId": 6,
    "rinterval": 6,
    "formationN": 0,
    "unitType": 5,
    "id": 210,
    "stime": 1
  },
  {
    "unitCnt": 6,
    "setId": 3,
    "unitId": 3,
    "poolId": 6,
    "rinterval": 6,
    "formationN": 0,
    "unitType": 5,
    "id": 211,
    "stime": 2
  },
  {
    "unitCnt": 1,
    "setId": 3,
    "unitId": 34,
    "poolId": 6,
    "rinterval": 0,
    "formationN": 0,
    "unitType": 6,
    "id": 212,
    "stime": 0
  },
  {
    "unitCnt": 2,
    "setId": 4,
    "unitId": 21,
    "poolId": 6,
    "rinterval": 6,
    "formationN": 0,
    "unitType": 5,
    "id": 213,
    "stime": 0.1
  },
  {
    "unitCnt": 4,
    "setId": 4,
    "unitId": 22,
    "poolId": 6,
    "rinterval": 6,
    "formationN": 0,
    "unitType": 5,
    "id": 214,
    "stime": 1
  },
  {
    "unitCnt": 2,
    "setId": 4,
    "unitId": 17,
    "poolId": 6,
    "rinterval": 6,
    "formationN": 0,
    "unitType": 5,
    "id": 215,
    "stime": 2
  },
  {
    "unitCnt": 1,
    "setId": 4,
    "unitId": 35,
    "poolId": 6,
    "rinterval": 0,
    "formationN": 0,
    "unitType": 6,
    "id": 216,
    "stime": 0
  },
  {
    "unitCnt": 10,
    "setId": 5,
    "unitId": 3,
    "poolId": 6,
    "rinterval": 6,
    "formationN": 0,
    "unitType": 5,
    "id": 217,
    "stime": 0.1
  },
  {
    "unitCnt": 8,
    "setId": 5,
    "unitId": 5,
    "poolId": 6,
    "rinterval": 6,
    "formationN": 0,
    "unitType": 5,
    "id": 218,
    "stime": 1
  },
  {
    "unitCnt": 6,
    "setId": 5,
    "unitId": 15,
    "poolId": 6,
    "rinterval": 6,
    "formationN": 0,
    "unitType": 5,
    "id": 219,
    "stime": 2
  },
  {
    "unitCnt": 1,
    "setId": 5,
    "unitId": 36,
    "poolId": 6,
    "rinterval": 0,
    "formationN": 0,
    "unitType": 6,
    "id": 220,
    "stime": 0
  },
  {
    "unitCnt": 2,
    "setId": 6,
    "unitId": 21,
    "poolId": 6,
    "rinterval": 6,
    "formationN": 0,
    "unitType": 5,
    "id": 221,
    "stime": 0.1
  },
  {
    "unitCnt": 4,
    "setId": 6,
    "unitId": 6,
    "poolId": 6,
    "rinterval": 6,
    "formationN": 0,
    "unitType": 5,
    "id": 222,
    "stime": 1
  },
  {
    "unitCnt": 2,
    "setId": 6,
    "unitId": 12,
    "poolId": 6,
    "rinterval": 6,
    "formationN": 0,
    "unitType": 5,
    "id": 223,
    "stime": 2
  },
  {
    "unitCnt": 1,
    "setId": 6,
    "unitId": 37,
    "poolId": 6,
    "rinterval": 0,
    "formationN": 0,
    "unitType": 6,
    "id": 224,
    "stime": 0
  },
  {
    "unitCnt": 6,
    "setId": 7,
    "unitId": 9,
    "poolId": 6,
    "rinterval": 6,
    "formationN": 0,
    "unitType": 5,
    "id": 225,
    "stime": 0.1
  },
  {
    "unitCnt": 5,
    "setId": 7,
    "unitId": 26,
    "poolId": 6,
    "rinterval": 6,
    "formationN": 0,
    "unitType": 5,
    "id": 226,
    "stime": 1
  },
  {
    "unitCnt": 3,
    "setId": 7,
    "unitId": 19,
    "poolId": 6,
    "rinterval": 6,
    "formationN": 0,
    "unitType": 5,
    "id": 227,
    "stime": 2
  },
  {
    "unitCnt": 1,
    "setId": 7,
    "unitId": 38,
    "poolId": 6,
    "rinterval": 0,
    "formationN": 0,
    "unitType": 6,
    "id": 228,
    "stime": 0
  },
  {
    "unitCnt": 10,
    "setId": 8,
    "unitId": 15,
    "poolId": 6,
    "rinterval": 6,
    "formationN": 5,
    "unitType": 5,
    "id": 229,
    "stime": 0.1
  },
  {
    "unitCnt": 8,
    "setId": 8,
    "unitId": 2,
    "poolId": 6,
    "rinterval": 6,
    "formationN": 4,
    "unitType": 5,
    "id": 230,
    "stime": 1
  },
  {
    "unitCnt": 6,
    "setId": 8,
    "unitId": 4,
    "poolId": 6,
    "rinterval": 6,
    "formationN": 3,
    "unitType": 5,
    "id": 231,
    "stime": 2
  },
  {
    "unitCnt": 1,
    "setId": 8,
    "unitId": 32,
    "poolId": 6,
    "rinterval": 0,
    "formationN": 0,
    "unitType": 6,
    "id": 232,
    "stime": 0
  },
  {
    "unitCnt": 2,
    "setId": 9,
    "unitId": 22,
    "poolId": 6,
    "rinterval": 6,
    "formationN": 2,
    "unitType": 5,
    "id": 233,
    "stime": 0.1
  },
  {
    "unitCnt": 4,
    "setId": 9,
    "unitId": 21,
    "poolId": 6,
    "rinterval": 6,
    "formationN": 2,
    "unitType": 5,
    "id": 234,
    "stime": 1
  },
  {
    "unitCnt": 2,
    "setId": 9,
    "unitId": 12,
    "poolId": 6,
    "rinterval": 6,
    "formationN": 2,
    "unitType": 5,
    "id": 235,
    "stime": 2
  },
  {
    "unitCnt": 1,
    "setId": 9,
    "unitId": 33,
    "poolId": 6,
    "rinterval": 0,
    "formationN": 0,
    "unitType": 6,
    "id": 236,
    "stime": 0
  },
  {
    "unitCnt": 10,
    "setId": 10,
    "unitId": 2,
    "poolId": 6,
    "rinterval": 6,
    "formationN": 5,
    "unitType": 5,
    "id": 237,
    "stime": 0.1
  },
  {
    "unitCnt": 8,
    "setId": 10,
    "unitId": 9,
    "poolId": 6,
    "rinterval": 6,
    "formationN": 4,
    "unitType": 5,
    "id": 238,
    "stime": 1
  },
  {
    "unitCnt": 6,
    "setId": 10,
    "unitId": 8,
    "poolId": 6,
    "rinterval": 6,
    "formationN": 3,
    "unitType": 5,
    "id": 239,
    "stime": 2
  },
  {
    "unitCnt": 1,
    "setId": 10,
    "unitId": 34,
    "poolId": 6,
    "rinterval": 0,
    "formationN": 0,
    "unitType": 6,
    "id": 240,
    "stime": 0
  },
  {
    "unitCnt": 2,
    "setId": 11,
    "unitId": 6,
    "poolId": 6,
    "rinterval": 6,
    "formationN": 2,
    "unitType": 5,
    "id": 241,
    "stime": 0.1
  },
  {
    "unitCnt": 4,
    "setId": 11,
    "unitId": 16,
    "poolId": 6,
    "rinterval": 6,
    "formationN": 2,
    "unitType": 5,
    "id": 242,
    "stime": 1
  },
  {
    "unitCnt": 2,
    "setId": 11,
    "unitId": 10,
    "poolId": 6,
    "rinterval": 6,
    "formationN": 2,
    "unitType": 5,
    "id": 243,
    "stime": 2
  },
  {
    "unitCnt": 1,
    "setId": 11,
    "unitId": 35,
    "poolId": 6,
    "rinterval": 0,
    "formationN": 0,
    "unitType": 6,
    "id": 244,
    "stime": 0
  },
  {
    "unitCnt": 10,
    "setId": 12,
    "unitId": 3,
    "poolId": 6,
    "rinterval": 6,
    "formationN": 5,
    "unitType": 5,
    "id": 245,
    "stime": 0.1
  },
  {
    "unitCnt": 8,
    "setId": 12,
    "unitId": 2,
    "poolId": 6,
    "rinterval": 6,
    "formationN": 4,
    "unitType": 5,
    "id": 246,
    "stime": 1
  },
  {
    "unitCnt": 6,
    "setId": 12,
    "unitId": 15,
    "poolId": 6,
    "rinterval": 6,
    "formationN": 3,
    "unitType": 5,
    "id": 247,
    "stime": 2
  },
  {
    "unitCnt": 1,
    "setId": 12,
    "unitId": 36,
    "poolId": 6,
    "rinterval": 0,
    "formationN": 0,
    "unitType": 6,
    "id": 248,
    "stime": 0
  },
  {
    "unitCnt": 2,
    "setId": 13,
    "unitId": 22,
    "poolId": 6,
    "rinterval": 6,
    "formationN": 2,
    "unitType": 5,
    "id": 249,
    "stime": 0.1
  },
  {
    "unitCnt": 4,
    "setId": 13,
    "unitId": 7,
    "poolId": 6,
    "rinterval": 6,
    "formationN": 2,
    "unitType": 5,
    "id": 250,
    "stime": 1
  },
  {
    "unitCnt": 2,
    "setId": 13,
    "unitId": 12,
    "poolId": 6,
    "rinterval": 6,
    "formationN": 2,
    "unitType": 5,
    "id": 251,
    "stime": 2
  },
  {
    "unitCnt": 1,
    "setId": 13,
    "unitId": 37,
    "poolId": 6,
    "rinterval": 0,
    "formationN": 0,
    "unitType": 6,
    "id": 252,
    "stime": 0
  },
  {
    "unitCnt": 6,
    "setId": 14,
    "unitId": 4,
    "poolId": 6,
    "rinterval": 6,
    "formationN": 3,
    "unitType": 5,
    "id": 253,
    "stime": 0.1
  },
  {
    "unitCnt": 5,
    "setId": 14,
    "unitId": 26,
    "poolId": 6,
    "rinterval": 6,
    "formationN": 5,
    "unitType": 5,
    "id": 254,
    "stime": 1
  },
  {
    "unitCnt": 3,
    "setId": 14,
    "unitId": 18,
    "poolId": 6,
    "rinterval": 6,
    "formationN": 3,
    "unitType": 5,
    "id": 255,
    "stime": 2
  },
  {
    "unitCnt": 1,
    "setId": 14,
    "unitId": 38,
    "poolId": 6,
    "rinterval": 0,
    "formationN": 0,
    "unitType": 6,
    "id": 256,
    "stime": 0
  },
  {
    "unitCnt": 6,
    "setId": 1,
    "unitId": 53,
    "poolId": 7,
    "rinterval": 6,
    "formationN": 0,
    "unitType": 5,
    "id": 257,
    "stime": 0.1
  },
  {
    "unitCnt": 4,
    "setId": 1,
    "unitId": 55,
    "poolId": 7,
    "rinterval": 6,
    "formationN": 0,
    "unitType": 5,
    "id": 258,
    "stime": 1
  },
  {
    "unitCnt": 1,
    "setId": 1,
    "unitId": 52,
    "poolId": 7,
    "rinterval": 6,
    "formationN": 0,
    "unitType": 5,
    "id": 259,
    "stime": 2
  },
  {
    "unitCnt": 1,
    "setId": 1,
    "unitId": 29,
    "poolId": 7,
    "rinterval": 0,
    "formationN": 0,
    "unitType": 6,
    "id": 260,
    "stime": 0
  },
  {
    "unitCnt": 4,
    "setId": 2,
    "unitId": 55,
    "poolId": 7,
    "rinterval": 6,
    "formationN": 0,
    "unitType": 5,
    "id": 261,
    "stime": 0.1
  },
  {
    "unitCnt": 6,
    "setId": 2,
    "unitId": 56,
    "poolId": 7,
    "rinterval": 6,
    "formationN": 0,
    "unitType": 5,
    "id": 262,
    "stime": 1
  },
  {
    "unitCnt": 2,
    "setId": 2,
    "unitId": 13,
    "poolId": 7,
    "rinterval": 6,
    "formationN": 0,
    "unitType": 5,
    "id": 263,
    "stime": 2
  },
  {
    "unitCnt": 1,
    "setId": 2,
    "unitId": 31,
    "poolId": 7,
    "rinterval": 0,
    "formationN": 0,
    "unitType": 6,
    "id": 264,
    "stime": 0
  },
  {
    "unitCnt": 8,
    "setId": 3,
    "unitId": 54,
    "poolId": 7,
    "rinterval": 6,
    "formationN": 0,
    "unitType": 5,
    "id": 265,
    "stime": 0.1
  },
  {
    "unitCnt": 6,
    "setId": 3,
    "unitId": 53,
    "poolId": 7,
    "rinterval": 6,
    "formationN": 0,
    "unitType": 5,
    "id": 266,
    "stime": 1
  },
  {
    "unitCnt": 6,
    "setId": 3,
    "unitId": 57,
    "poolId": 7,
    "rinterval": 6,
    "formationN": 0,
    "unitType": 5,
    "id": 267,
    "stime": 2
  },
  {
    "unitCnt": 1,
    "setId": 3,
    "unitId": 33,
    "poolId": 7,
    "rinterval": 0,
    "formationN": 0,
    "unitType": 6,
    "id": 268,
    "stime": 0
  },
  {
    "unitCnt": 4,
    "setId": 4,
    "unitId": 58,
    "poolId": 7,
    "rinterval": 6,
    "formationN": 0,
    "unitType": 5,
    "id": 269,
    "stime": 0.1
  },
  {
    "unitCnt": 6,
    "setId": 4,
    "unitId": 55,
    "poolId": 7,
    "rinterval": 6,
    "formationN": 0,
    "unitType": 5,
    "id": 270,
    "stime": 1
  },
  {
    "unitCnt": 2,
    "setId": 4,
    "unitId": 12,
    "poolId": 7,
    "rinterval": 6,
    "formationN": 0,
    "unitType": 5,
    "id": 271,
    "stime": 2
  },
  {
    "unitCnt": 1,
    "setId": 4,
    "unitId": 35,
    "poolId": 7,
    "rinterval": 0,
    "formationN": 0,
    "unitType": 6,
    "id": 272,
    "stime": 0
  },
  {
    "unitCnt": 4,
    "setId": 5,
    "unitId": 58,
    "poolId": 7,
    "rinterval": 6,
    "formationN": 0,
    "unitType": 5,
    "id": 273,
    "stime": 0.1
  },
  {
    "unitCnt": 6,
    "setId": 5,
    "unitId": 53,
    "poolId": 7,
    "rinterval": 6,
    "formationN": 0,
    "unitType": 5,
    "id": 274,
    "stime": 1
  },
  {
    "unitCnt": 2,
    "setId": 5,
    "unitId": 52,
    "poolId": 7,
    "rinterval": 6,
    "formationN": 0,
    "unitType": 5,
    "id": 275,
    "stime": 2
  },
  {
    "unitCnt": 1,
    "setId": 5,
    "unitId": 37,
    "poolId": 7,
    "rinterval": 0,
    "formationN": 0,
    "unitType": 6,
    "id": 276,
    "stime": 0
  },
  {
    "unitCnt": 6,
    "setId": 6,
    "unitId": 55,
    "poolId": 7,
    "rinterval": 6,
    "formationN": 3,
    "unitType": 5,
    "id": 277,
    "stime": 0.1
  },
  {
    "unitCnt": 4,
    "setId": 6,
    "unitId": 53,
    "poolId": 7,
    "rinterval": 6,
    "formationN": 2,
    "unitType": 5,
    "id": 278,
    "stime": 1
  },
  {
    "unitCnt": 2,
    "setId": 6,
    "unitId": 51,
    "poolId": 7,
    "rinterval": 6,
    "formationN": 3,
    "unitType": 5,
    "id": 279,
    "stime": 2
  },
  {
    "unitCnt": 1,
    "setId": 6,
    "unitId": 39,
    "poolId": 7,
    "rinterval": 0,
    "formationN": 0,
    "unitType": 6,
    "id": 280,
    "stime": 0
  },
  {
    "unitCnt": 4,
    "setId": 7,
    "unitId": 56,
    "poolId": 7,
    "rinterval": 6,
    "formationN": 2,
    "unitType": 5,
    "id": 281,
    "stime": 0.1
  },
  {
    "unitCnt": 6,
    "setId": 7,
    "unitId": 55,
    "poolId": 7,
    "rinterval": 6,
    "formationN": 3,
    "unitType": 5,
    "id": 282,
    "stime": 1
  },
  {
    "unitCnt": 2,
    "setId": 7,
    "unitId": 10,
    "poolId": 7,
    "rinterval": 6,
    "formationN": 2,
    "unitType": 5,
    "id": 283,
    "stime": 2
  },
  {
    "unitCnt": 1,
    "setId": 7,
    "unitId": 30,
    "poolId": 7,
    "rinterval": 0,
    "formationN": 0,
    "unitType": 6,
    "id": 284,
    "stime": 0
  },
  {
    "unitCnt": 8,
    "setId": 8,
    "unitId": 54,
    "poolId": 7,
    "rinterval": 6,
    "formationN": 4,
    "unitType": 5,
    "id": 285,
    "stime": 0.1
  },
  {
    "unitCnt": 6,
    "setId": 8,
    "unitId": 53,
    "poolId": 7,
    "rinterval": 6,
    "formationN": 3,
    "unitType": 5,
    "id": 286,
    "stime": 1
  },
  {
    "unitCnt": 6,
    "setId": 8,
    "unitId": 57,
    "poolId": 7,
    "rinterval": 6,
    "formationN": 3,
    "unitType": 5,
    "id": 287,
    "stime": 2
  },
  {
    "unitCnt": 1,
    "setId": 8,
    "unitId": 32,
    "poolId": 7,
    "rinterval": 0,
    "formationN": 0,
    "unitType": 6,
    "id": 288,
    "stime": 0
  },
  {
    "unitCnt": 4,
    "setId": 9,
    "unitId": 58,
    "poolId": 7,
    "rinterval": 6,
    "formationN": 2,
    "unitType": 5,
    "id": 289,
    "stime": 0.1
  },
  {
    "unitCnt": 6,
    "setId": 9,
    "unitId": 55,
    "poolId": 7,
    "rinterval": 6,
    "formationN": 3,
    "unitType": 5,
    "id": 290,
    "stime": 1
  },
  {
    "unitCnt": 2,
    "setId": 9,
    "unitId": 13,
    "poolId": 7,
    "rinterval": 6,
    "formationN": 2,
    "unitType": 5,
    "id": 291,
    "stime": 2
  },
  {
    "unitCnt": 1,
    "setId": 9,
    "unitId": 34,
    "poolId": 7,
    "rinterval": 0,
    "formationN": 0,
    "unitType": 6,
    "id": 292,
    "stime": 0
  },
  {
    "unitCnt": 4,
    "setId": 10,
    "unitId": 53,
    "poolId": 7,
    "rinterval": 6,
    "formationN": 2,
    "unitType": 5,
    "id": 293,
    "stime": 0.1
  },
  {
    "unitCnt": 6,
    "setId": 10,
    "unitId": 57,
    "poolId": 7,
    "rinterval": 6,
    "formationN": 3,
    "unitType": 5,
    "id": 294,
    "stime": 1
  },
  {
    "unitCnt": 2,
    "setId": 10,
    "unitId": 51,
    "poolId": 7,
    "rinterval": 6,
    "formationN": 3,
    "unitType": 5,
    "id": 295,
    "stime": 2
  },
  {
    "unitCnt": 1,
    "setId": 10,
    "unitId": 36,
    "poolId": 7,
    "rinterval": 0,
    "formationN": 0,
    "unitType": 6,
    "id": 296,
    "stime": 0
  },
  {
    "unitCnt": 4,
    "setId": 11,
    "unitId": 53,
    "poolId": 7,
    "rinterval": 6,
    "formationN": 0,
    "unitType": 5,
    "id": 297,
    "stime": 0.1
  },
  {
    "unitCnt": 3,
    "setId": 11,
    "unitId": 51,
    "poolId": 7,
    "rinterval": 6,
    "formationN": 0,
    "unitType": 5,
    "id": 298,
    "stime": 1
  },
  {
    "unitCnt": 1,
    "setId": 11,
    "unitId": 52,
    "poolId": 7,
    "rinterval": 6,
    "formationN": 0,
    "unitType": 5,
    "id": 299,
    "stime": 2
  },
  {
    "unitCnt": 1,
    "setId": 11,
    "unitId": 38,
    "poolId": 7,
    "rinterval": 0,
    "formationN": 0,
    "unitType": 6,
    "id": 300,
    "stime": 0
  },
  {
    "unitCnt": 6,
    "setId": 12,
    "unitId": 55,
    "poolId": 7,
    "rinterval": 6,
    "formationN": 0,
    "unitType": 5,
    "id": 301,
    "stime": 0.1
  },
  {
    "unitCnt": 4,
    "setId": 12,
    "unitId": 53,
    "poolId": 7,
    "rinterval": 6,
    "formationN": 0,
    "unitType": 5,
    "id": 302,
    "stime": 1
  },
  {
    "unitCnt": 1,
    "setId": 12,
    "unitId": 51,
    "poolId": 7,
    "rinterval": 6,
    "formationN": 0,
    "unitType": 5,
    "id": 303,
    "stime": 2
  },
  {
    "unitCnt": 1,
    "setId": 12,
    "unitId": 40,
    "poolId": 7,
    "rinterval": 0,
    "formationN": 0,
    "unitType": 6,
    "id": 304,
    "stime": 0
  },
  {
    "unitCnt": 4,
    "setId": 13,
    "unitId": 56,
    "poolId": 7,
    "rinterval": 6,
    "formationN": 0,
    "unitType": 5,
    "id": 305,
    "stime": 0.1
  },
  {
    "unitCnt": 6,
    "setId": 13,
    "unitId": 55,
    "poolId": 7,
    "rinterval": 6,
    "formationN": 0,
    "unitType": 5,
    "id": 306,
    "stime": 1
  },
  {
    "unitCnt": 2,
    "setId": 13,
    "unitId": 10,
    "poolId": 7,
    "rinterval": 6,
    "formationN": 0,
    "unitType": 5,
    "id": 307,
    "stime": 2
  },
  {
    "unitCnt": 1,
    "setId": 13,
    "unitId": 42,
    "poolId": 7,
    "rinterval": 0,
    "formationN": 0,
    "unitType": 6,
    "id": 308,
    "stime": 0
  },
  {
    "unitCnt": 8,
    "setId": 14,
    "unitId": 54,
    "poolId": 7,
    "rinterval": 6,
    "formationN": 0,
    "unitType": 5,
    "id": 309,
    "stime": 0.1
  },
  {
    "unitCnt": 6,
    "setId": 14,
    "unitId": 53,
    "poolId": 7,
    "rinterval": 6,
    "formationN": 0,
    "unitType": 5,
    "id": 310,
    "stime": 1
  },
  {
    "unitCnt": 6,
    "setId": 14,
    "unitId": 57,
    "poolId": 7,
    "rinterval": 6,
    "formationN": 0,
    "unitType": 5,
    "id": 311,
    "stime": 2
  },
  {
    "unitCnt": 1,
    "setId": 14,
    "unitId": 44,
    "poolId": 7,
    "rinterval": 0,
    "formationN": 0,
    "unitType": 6,
    "id": 312,
    "stime": 0
  },
  {
    "unitCnt": 4,
    "setId": 15,
    "unitId": 58,
    "poolId": 7,
    "rinterval": 6,
    "formationN": 0,
    "unitType": 5,
    "id": 313,
    "stime": 0.1
  },
  {
    "unitCnt": 6,
    "setId": 15,
    "unitId": 55,
    "poolId": 7,
    "rinterval": 6,
    "formationN": 0,
    "unitType": 5,
    "id": 314,
    "stime": 1
  },
  {
    "unitCnt": 2,
    "setId": 15,
    "unitId": 13,
    "poolId": 7,
    "rinterval": 6,
    "formationN": 0,
    "unitType": 5,
    "id": 315,
    "stime": 2
  },
  {
    "unitCnt": 1,
    "setId": 15,
    "unitId": 46,
    "poolId": 7,
    "rinterval": 0,
    "formationN": 0,
    "unitType": 6,
    "id": 316,
    "stime": 0
  },
  {
    "unitCnt": 4,
    "setId": 16,
    "unitId": 53,
    "poolId": 7,
    "rinterval": 6,
    "formationN": 0,
    "unitType": 5,
    "id": 317,
    "stime": 0.1
  },
  {
    "unitCnt": 6,
    "setId": 16,
    "unitId": 57,
    "poolId": 7,
    "rinterval": 6,
    "formationN": 0,
    "unitType": 5,
    "id": 318,
    "stime": 1
  },
  {
    "unitCnt": 2,
    "setId": 16,
    "unitId": 51,
    "poolId": 7,
    "rinterval": 6,
    "formationN": 0,
    "unitType": 5,
    "id": 319,
    "stime": 2
  },
  {
    "unitCnt": 1,
    "setId": 16,
    "unitId": 48,
    "poolId": 7,
    "rinterval": 0,
    "formationN": 0,
    "unitType": 6,
    "id": 320,
    "stime": 0
  },
  {
    "unitCnt": 6,
    "setId": 17,
    "unitId": 53,
    "poolId": 7,
    "rinterval": 6,
    "formationN": 3,
    "unitType": 5,
    "id": 321,
    "stime": 0.1
  },
  {
    "unitCnt": 6,
    "setId": 17,
    "unitId": 55,
    "poolId": 7,
    "rinterval": 6,
    "formationN": 3,
    "unitType": 5,
    "id": 322,
    "stime": 1
  },
  {
    "unitCnt": 2,
    "setId": 17,
    "unitId": 52,
    "poolId": 7,
    "rinterval": 6,
    "formationN": 2,
    "unitType": 5,
    "id": 323,
    "stime": 2
  },
  {
    "unitCnt": 1,
    "setId": 17,
    "unitId": 50,
    "poolId": 7,
    "rinterval": 0,
    "formationN": 0,
    "unitType": 6,
    "id": 324,
    "stime": 0
  },
  {
    "unitCnt": 4,
    "setId": 18,
    "unitId": 55,
    "poolId": 7,
    "rinterval": 6,
    "formationN": 2,
    "unitType": 5,
    "id": 325,
    "stime": 0.1
  },
  {
    "unitCnt": 6,
    "setId": 18,
    "unitId": 56,
    "poolId": 7,
    "rinterval": 6,
    "formationN": 3,
    "unitType": 5,
    "id": 326,
    "stime": 1
  },
  {
    "unitCnt": 2,
    "setId": 18,
    "unitId": 13,
    "poolId": 7,
    "rinterval": 6,
    "formationN": 2,
    "unitType": 5,
    "id": 327,
    "stime": 2
  },
  {
    "unitCnt": 1,
    "setId": 18,
    "unitId": 41,
    "poolId": 7,
    "rinterval": 0,
    "formationN": 0,
    "unitType": 6,
    "id": 328,
    "stime": 0
  },
  {
    "unitCnt": 8,
    "setId": 19,
    "unitId": 54,
    "poolId": 7,
    "rinterval": 6,
    "formationN": 4,
    "unitType": 5,
    "id": 329,
    "stime": 0.1
  },
  {
    "unitCnt": 6,
    "setId": 19,
    "unitId": 53,
    "poolId": 7,
    "rinterval": 6,
    "formationN": 3,
    "unitType": 5,
    "id": 330,
    "stime": 1
  },
  {
    "unitCnt": 6,
    "setId": 19,
    "unitId": 57,
    "poolId": 7,
    "rinterval": 6,
    "formationN": 3,
    "unitType": 5,
    "id": 331,
    "stime": 2
  },
  {
    "unitCnt": 1,
    "setId": 19,
    "unitId": 43,
    "poolId": 7,
    "rinterval": 0,
    "formationN": 0,
    "unitType": 6,
    "id": 332,
    "stime": 0
  },
  {
    "unitCnt": 4,
    "setId": 20,
    "unitId": 58,
    "poolId": 7,
    "rinterval": 6,
    "formationN": 2,
    "unitType": 5,
    "id": 333,
    "stime": 0.1
  },
  {
    "unitCnt": 6,
    "setId": 20,
    "unitId": 55,
    "poolId": 7,
    "rinterval": 6,
    "formationN": 3,
    "unitType": 5,
    "id": 334,
    "stime": 1
  },
  {
    "unitCnt": 2,
    "setId": 20,
    "unitId": 12,
    "poolId": 7,
    "rinterval": 6,
    "formationN": 2,
    "unitType": 5,
    "id": 335,
    "stime": 2
  },
  {
    "unitCnt": 1,
    "setId": 20,
    "unitId": 45,
    "poolId": 7,
    "rinterval": 0,
    "formationN": 0,
    "unitType": 6,
    "id": 336,
    "stime": 0
  },
  {
    "unitCnt": 6,
    "setId": 21,
    "unitId": 58,
    "poolId": 7,
    "rinterval": 6,
    "formationN": 3,
    "unitType": 5,
    "id": 337,
    "stime": 0.1
  },
  {
    "unitCnt": 4,
    "setId": 21,
    "unitId": 53,
    "poolId": 7,
    "rinterval": 6,
    "formationN": 2,
    "unitType": 5,
    "id": 338,
    "stime": 1
  },
  {
    "unitCnt": 2,
    "setId": 21,
    "unitId": 52,
    "poolId": 7,
    "rinterval": 6,
    "formationN": 2,
    "unitType": 5,
    "id": 339,
    "stime": 2
  },
  {
    "unitCnt": 1,
    "setId": 21,
    "unitId": 47,
    "poolId": 7,
    "rinterval": 0,
    "formationN": 0,
    "unitType": 6,
    "id": 340,
    "stime": 0
  },
  {
    "unitCnt": 1,
    "setId": 22,
    "unitId": 13,
    "poolId": 7,
    "rinterval": 6,
    "formationN": 0,
    "unitType": 5,
    "id": 341,
    "stime": 0.1
  },
  {
    "unitCnt": 3,
    "setId": 22,
    "unitId": 55,
    "poolId": 7,
    "rinterval": 6,
    "formationN": 0,
    "unitType": 5,
    "id": 342,
    "stime": 1
  },
  {
    "unitCnt": 2,
    "setId": 22,
    "unitId": 52,
    "poolId": 7,
    "rinterval": 6,
    "formationN": 0,
    "unitType": 5,
    "id": 343,
    "stime": 2
  },
  {
    "unitCnt": 1,
    "setId": 22,
    "unitId": 49,
    "poolId": 7,
    "rinterval": 0,
    "formationN": 0,
    "unitType": 6,
    "id": 344,
    "stime": 0
  }
]
